<annotation>
	<folder>bread</folder>
	<filename>WIN_20200413_20_40_10_Pro.jpg</filename>
	<path>D:\b10613110\bread\WIN_20200413_20_40_10_Pro.jpg</path>
	<source>
		<database>Unknown</database>
	</source>
	<size>
		<width>1280</width>
		<height>720</height>
		<depth>3</depth>
	</size>
	<segmented>0</segmented>
	<object>
		<name>twist bread</name>
		<pose>Unspecified</pose>
		<truncated>0</truncated>
		<difficult>0</difficult>
		<bndbox>
			<xmin>789</xmin>
			<ymin>235</ymin>
			<xmax>1007</xmax>
			<ymax>436</ymax>
		</bndbox>
	</object>
	<object>
		<name>bun</name>
		<pose>Unspecified</pose>
		<truncated>0</truncated>
		<difficult>0</difficult>
		<bndbox>
			<xmin>275</xmin>
			<ymin>376</ymin>
			<xmax>477</xmax>
			<ymax>573</ymax>
		</bndbox>
	</object>
</annotation>
