<annotation>
	<folder>兩個</folder>
	<filename>WIN_20200603_15_05_46_Pro.jpg</filename>
	<path>D:\Users\User\Desktop\0603混拍\兩個\WIN_20200603_15_05_46_Pro.jpg</path>
	<source>
		<database>Unknown</database>
	</source>
	<size>
		<width>1280</width>
		<height>720</height>
		<depth>3</depth>
	</size>
	<segmented>0</segmented>
	<object>
		<name>hamburger</name>
		<pose>Unspecified</pose>
		<truncated>0</truncated>
		<difficult>0</difficult>
		<bndbox>
			<xmin>658</xmin>
			<ymin>187</ymin>
			<xmax>956</xmax>
			<ymax>464</ymax>
		</bndbox>
	</object>
	<object>
		<name>yellow pear</name>
		<pose>Unspecified</pose>
		<truncated>0</truncated>
		<difficult>0</difficult>
		<bndbox>
			<xmin>309</xmin>
			<ymin>248</ymin>
			<xmax>515</xmax>
			<ymax>466</ymax>
		</bndbox>
	</object>
</annotation>
