<annotation>
	<folder>三個</folder>
	<filename>WIN_20200603_18_12_11_Pro.jpg</filename>
	<path>D:\Users\User\Desktop\0603混拍\三個\WIN_20200603_18_12_11_Pro.jpg</path>
	<source>
		<database>Unknown</database>
	</source>
	<size>
		<width>1280</width>
		<height>720</height>
		<depth>3</depth>
	</size>
	<segmented>0</segmented>
	<object>
		<name>sandwich</name>
		<pose>Unspecified</pose>
		<truncated>0</truncated>
		<difficult>0</difficult>
		<bndbox>
			<xmin>676</xmin>
			<ymin>361</ymin>
			<xmax>1045</xmax>
			<ymax>579</ymax>
		</bndbox>
	</object>
	<object>
		<name>green pear</name>
		<pose>Unspecified</pose>
		<truncated>0</truncated>
		<difficult>0</difficult>
		<bndbox>
			<xmin>186</xmin>
			<ymin>228</ymin>
			<xmax>447</xmax>
			<ymax>430</ymax>
		</bndbox>
	</object>
	<object>
		<name>red mango</name>
		<pose>Unspecified</pose>
		<truncated>0</truncated>
		<difficult>0</difficult>
		<bndbox>
			<xmin>626</xmin>
			<ymin>85</ymin>
			<xmax>965</xmax>
			<ymax>296</ymax>
		</bndbox>
	</object>
</annotation>
