<annotation>
	<folder>Fruit</folder>
	<filename>WIN_20200325_21_01_32_Pro.jpg</filename>
	<path>D:\Fruit\WIN_20200325_21_01_32_Pro.jpg</path>
	<source>
		<database>Unknown</database>
	</source>
	<size>
		<width>1280</width>
		<height>720</height>
		<depth>3</depth>
	</size>
	<segmented>0</segmented>
	<object>
		<name>papya</name>
		<pose>Unspecified</pose>
		<truncated>0</truncated>
		<difficult>0</difficult>
		<bndbox>
			<xmin>402</xmin>
			<ymin>196</ymin>
			<xmax>623</xmax>
			<ymax>424</ymax>
		</bndbox>
	</object>
	<object>
		<name>orange</name>
		<pose>Unspecified</pose>
		<truncated>0</truncated>
		<difficult>0</difficult>
		<bndbox>
			<xmin>250</xmin>
			<ymin>179</ymin>
			<xmax>437</xmax>
			<ymax>348</ymax>
		</bndbox>
	</object>
	<object>
		<name>red mango</name>
		<pose>Unspecified</pose>
		<truncated>0</truncated>
		<difficult>0</difficult>
		<bndbox>
			<xmin>582</xmin>
			<ymin>173</ymin>
			<xmax>787</xmax>
			<ymax>406</ymax>
		</bndbox>
	</object>
	<object>
		<name>red apple</name>
		<pose>Unspecified</pose>
		<truncated>0</truncated>
		<difficult>0</difficult>
		<bndbox>
			<xmin>260</xmin>
			<ymin>313</ymin>
			<xmax>587</xmax>
			<ymax>628</ymax>
		</bndbox>
	</object>
</annotation>
